<?xml version="1.0" encoding="US-ASCII"?>
<xl-ddm-data database="" description="eFBS Citrix Terminal Services Connector Configuration 12.2.1.3" exported-date="1549479574220" user="XELSYSADM" version="12.2.1.3.0">
  <Lookup name="Lookup.CTS.Organization" repo-type="RDBMS" subtype="Lookup">
    <LKU_GROUP>ADS</LKU_GROUP>
    <LKU_UPDATE>1549479574220</LKU_UPDATE>
    <LKU_REQUIRED>0</LKU_REQUIRED>
    <LKU_TYPE>l</LKU_TYPE>
    <LKU_MEANING>Active Directory Organizational Unit List</LKU_MEANING>
    <LookupValue id="LKV4551" repo-type="RDBMS">
      <LKV_UPDATE>1549479574220</LKV_UPDATE>
      <LKV_ENCODED>29~ou=AN,ou=App,dc=bka,dc=bund,dc=de</LKV_ENCODED>
      <LKV_LANGUAGE>en</LKV_LANGUAGE>
      <LKV_COUNTRY>US</LKV_COUNTRY>
      <LKV_DISABLED>0</LKV_DISABLED>
      <LKV_DECODED>TS.ADS Endpoint~ou=AN,ou=App,dc=bka,dc=bund,dc=de</LKV_DECODED>
    </LookupValue>
    <LookupValue id="LKV4552" repo-type="RDBMS">
      <LKV_UPDATE>1549479574220</LKV_UPDATE>
      <LKV_ENCODED>29~ou=BB,ou=App,dc=bka,dc=bund,dc=de</LKV_ENCODED>
      <LKV_LANGUAGE>en</LKV_LANGUAGE>
      <LKV_COUNTRY>US</LKV_COUNTRY>
      <LKV_DISABLED>0</LKV_DISABLED>
      <LKV_DECODED>TS.ADS Endpoint~ou=BB,ou=App,dc=bka,dc=bund,dc=de</LKV_DECODED>
    </LookupValue>
    <LookupValue id="LKV4553" repo-type="RDBMS">
      <LKV_UPDATE>1549479574220</LKV_UPDATE>
      <LKV_ENCODED>29~ou=BE,ou=App,dc=bka,dc=bund,dc=de</LKV_ENCODED>
      <LKV_LANGUAGE>en</LKV_LANGUAGE>
      <LKV_COUNTRY>US</LKV_COUNTRY>
      <LKV_DISABLED>0</LKV_DISABLED>
      <LKV_DECODED>TS.ADS Endpoint~ou=BE,ou=App,dc=bka,dc=bund,dc=de</LKV_DECODED>
    </LookupValue>
    <LookupValue id="LKV4554" repo-type="RDBMS">
      <LKV_UPDATE>1549479574220</LKV_UPDATE>
      <LKV_ENCODED>29~ou=BK,ou=App,dc=bka,dc=bund,dc=de</LKV_ENCODED>
      <LKV_LANGUAGE>en</LKV_LANGUAGE>
      <LKV_COUNTRY>US</LKV_COUNTRY>
      <LKV_DISABLED>0</LKV_DISABLED>
      <LKV_DECODED>TS.ADS Endpoint~ou=BK,ou=App,dc=bka,dc=bund,dc=de</LKV_DECODED>
    </LookupValue>
    <LookupValue id="LKV4555" repo-type="RDBMS">
      <LKV_UPDATE>1549479574220</LKV_UPDATE>
      <LKV_ENCODED>29~ou=BP,ou=App,dc=bka,dc=bund,dc=de</LKV_ENCODED>
      <LKV_LANGUAGE>en</LKV_LANGUAGE>
      <LKV_COUNTRY>US</LKV_COUNTRY>
      <LKV_DISABLED>0</LKV_DISABLED>
      <LKV_DECODED>TS.ADS Endpoint~ou=BP,ou=App,dc=bka,dc=bund,dc=de</LKV_DECODED>
    </LookupValue>
    <LookupValue id="LKV4556" repo-type="RDBMS">
      <LKV_UPDATE>1549479574220</LKV_UPDATE>
      <LKV_ENCODED>29~ou=BW,ou=App,dc=bka,dc=bund,dc=de</LKV_ENCODED>
      <LKV_LANGUAGE>en</LKV_LANGUAGE>
      <LKV_COUNTRY>US</LKV_COUNTRY>
      <LKV_DISABLED>0</LKV_DISABLED>
      <LKV_DECODED>TS.ADS Endpoint~ou=BW,ou=App,dc=bka,dc=bund,dc=de</LKV_DECODED>
    </LookupValue>
    <LookupValue id="LKV4557" repo-type="RDBMS">
      <LKV_UPDATE>1549479574220</LKV_UPDATE>
      <LKV_ENCODED>29~ou=BY,ou=App,dc=bka,dc=bund,dc=de</LKV_ENCODED>
      <LKV_LANGUAGE>en</LKV_LANGUAGE>
      <LKV_COUNTRY>US</LKV_COUNTRY>
      <LKV_DISABLED>0</LKV_DISABLED>
      <LKV_DECODED>TS.ADS Endpoint~ou=BY,ou=App,dc=bka,dc=bund,dc=de</LKV_DECODED>
    </LookupValue>
    <LookupValue id="LKV4558" repo-type="RDBMS">
      <LKV_UPDATE>1549479574220</LKV_UPDATE>
      <LKV_ENCODED>29~ou=HB,ou=App,dc=bka,dc=bund,dc=de</LKV_ENCODED>
      <LKV_LANGUAGE>en</LKV_LANGUAGE>
      <LKV_COUNTRY>US</LKV_COUNTRY>
      <LKV_DISABLED>0</LKV_DISABLED>
      <LKV_DECODED>TS.ADS Endpoint~ou=HB,ou=App,dc=bka,dc=bund,dc=de</LKV_DECODED>
    </LookupValue>
    <LookupValue id="LKV4559" repo-type="RDBMS">
      <LKV_UPDATE>1549479574220</LKV_UPDATE>
      <LKV_ENCODED>29~ou=HE,ou=App,dc=bka,dc=bund,dc=de</LKV_ENCODED>
      <LKV_LANGUAGE>en</LKV_LANGUAGE>
      <LKV_COUNTRY>US</LKV_COUNTRY>
      <LKV_DISABLED>0</LKV_DISABLED>
      <LKV_DECODED>TS.ADS Endpoint~ou=HE,ou=App,dc=bka,dc=bund,dc=de</LKV_DECODED>
    </LookupValue>
    <LookupValue id="LKV4560" repo-type="RDBMS">
      <LKV_UPDATE>1549479574220</LKV_UPDATE>
      <LKV_ENCODED>29~ou=HH,ou=App,dc=bka,dc=bund,dc=de</LKV_ENCODED>
      <LKV_LANGUAGE>en</LKV_LANGUAGE>
      <LKV_COUNTRY>US</LKV_COUNTRY>
      <LKV_DISABLED>0</LKV_DISABLED>
      <LKV_DECODED>TS.ADS Endpoint~ou=HH,ou=App,dc=bka,dc=bund,dc=de</LKV_DECODED>
    </LookupValue>
    <LookupValue id="LKV4561" repo-type="RDBMS">
      <LKV_UPDATE>1549479574220</LKV_UPDATE>
      <LKV_ENCODED>29~ou=MV,ou=App,dc=bka,dc=bund,dc=de</LKV_ENCODED>
      <LKV_LANGUAGE>en</LKV_LANGUAGE>
      <LKV_COUNTRY>US</LKV_COUNTRY>
      <LKV_DISABLED>0</LKV_DISABLED>
      <LKV_DECODED>TS.ADS Endpoint~ou=MV,ou=App,dc=bka,dc=bund,dc=de</LKV_DECODED>
    </LookupValue>
    <LookupValue id="LKV4562" repo-type="RDBMS">
      <LKV_UPDATE>1549479574220</LKV_UPDATE>
      <LKV_ENCODED>29~ou=NI,ou=App,dc=bka,dc=bund,dc=de</LKV_ENCODED>
      <LKV_LANGUAGE>en</LKV_LANGUAGE>
      <LKV_DISABLED>0</LKV_DISABLED>
      <LKV_COUNTRY>US</LKV_COUNTRY>
      <LKV_DECODED>TS.ADS Endpoint~ou=NI,ou=App,dc=bka,dc=bund,dc=de</LKV_DECODED>
    </LookupValue>
    <LookupValue id="LKV4563" repo-type="RDBMS">
      <LKV_UPDATE>1549479574220</LKV_UPDATE>
      <LKV_ENCODED>29~ou=NW,ou=App,dc=bka,dc=bund,dc=de</LKV_ENCODED>
      <LKV_LANGUAGE>en</LKV_LANGUAGE>
      <LKV_COUNTRY>US</LKV_COUNTRY>
      <LKV_DISABLED>0</LKV_DISABLED>
      <LKV_DECODED>TS.ADS Endpoint~ou=NW,ou=App,dc=bka,dc=bund,dc=de</LKV_DECODED>
    </LookupValue>
    <LookupValue id="LKV4564" repo-type="RDBMS">
      <LKV_UPDATE>1549479574220</LKV_UPDATE>
      <LKV_ENCODED>29~ou=RP,ou=App,dc=bka,dc=bund,dc=de</LKV_ENCODED>
      <LKV_LANGUAGE>en</LKV_LANGUAGE>
      <LKV_COUNTRY>US</LKV_COUNTRY>
      <LKV_DISABLED>0</LKV_DISABLED>
      <LKV_DECODED>TS.ADS Endpoint~ou=RP,ou=App,dc=bka,dc=bund,dc=de</LKV_DECODED>
    </LookupValue>
    <LookupValue id="LKV4565" repo-type="RDBMS">
      <LKV_UPDATE>1549479574220</LKV_UPDATE>
      <LKV_ENCODED>29~ou=SH,ou=App,dc=bka,dc=bund,dc=de</LKV_ENCODED>
      <LKV_LANGUAGE>en</LKV_LANGUAGE>
      <LKV_COUNTRY>US</LKV_COUNTRY>
      <LKV_DISABLED>0</LKV_DISABLED>
      <LKV_DECODED>TS.ADS Endpoint~ou=SH,ou=App,dc=bka,dc=bund,dc=de</LKV_DECODED>
    </LookupValue>
    <LookupValue id="LKV4566" repo-type="RDBMS">
      <LKV_UPDATE>1549479574220</LKV_UPDATE>
      <LKV_ENCODED>29~ou=SL,ou=App,dc=bka,dc=bund,dc=de</LKV_ENCODED>
      <LKV_LANGUAGE>en</LKV_LANGUAGE>
      <LKV_COUNTRY>US</LKV_COUNTRY>
      <LKV_DISABLED>0</LKV_DISABLED>
      <LKV_DECODED>TS.ADS Endpoint~ou=SL,ou=App,dc=bka,dc=bund,dc=de</LKV_DECODED>
    </LookupValue>
    <LookupValue id="LKV4567" repo-type="RDBMS">
      <LKV_UPDATE>1549479574220</LKV_UPDATE>
      <LKV_ENCODED>29~ou=SN,ou=App,dc=bka,dc=bund,dc=de</LKV_ENCODED>
      <LKV_LANGUAGE>en</LKV_LANGUAGE>
      <LKV_COUNTRY>US</LKV_COUNTRY>
      <LKV_DISABLED>0</LKV_DISABLED>
      <LKV_DECODED>TS.ADS Endpoint~ou=SN,ou=App,dc=bka,dc=bund,dc=de</LKV_DECODED>
    </LookupValue>
    <LookupValue id="LKV4568" repo-type="RDBMS">
      <LKV_UPDATE>1549479574220</LKV_UPDATE>
      <LKV_ENCODED>29~ou=TH,ou=App,dc=bka,dc=bund,dc=de</LKV_ENCODED>
      <LKV_LANGUAGE>en</LKV_LANGUAGE>
      <LKV_COUNTRY>US</LKV_COUNTRY>
      <LKV_DISABLED>0</LKV_DISABLED>
      <LKV_DECODED>TS.ADS Endpoint~ou=TH,ou=App,dc=bka,dc=bund,dc=de</LKV_DECODED>
    </LookupValue>
    <LookupValue id="LKV4569" repo-type="RDBMS">
      <LKV_UPDATE>1549479574220</LKV_UPDATE>
      <LKV_ENCODED>29~ou=ZF,ou=App,dc=bka,dc=bund,dc=de</LKV_ENCODED>
      <LKV_LANGUAGE>en</LKV_LANGUAGE>
      <LKV_COUNTRY>US</LKV_COUNTRY>
      <LKV_DISABLED>0</LKV_DISABLED>
      <LKV_DECODED>TS.ADS Endpoint~ou=ZF,ou=App,dc=bka,dc=bund,dc=de</LKV_DECODED>
    </LookupValue>
  </Lookup>
</xl-ddm-data>
